cel/__init__.py
cel/__init__.pyi
cel/_cel_python.pyi
cel/_cel_python.so
cel/proto.py
cel/pydantic.py
cel_bind-0.8.4.dist-info/WHEEL
cel_bind-0.8.4.dist-info/METADATA
cel_bind-0.8.4.dist-info/LICENSE
cel_bind-0.8.4.dist-info/RECORD
