Metadata-Version: 2.1
Name: cel_bind
Author: Enter
Home-page: https://github.com/getenter/cel-python
License: MIT
Classifier: Programming Language :: Python :: 3
Classifier: Programming Language :: C++
Classifier: Development Status :: 4 - Beta
Classifier: Operating System :: POSIX :: Linux
Classifier: Operating System :: MacOS
Requires-Python: >=3.10
Version: 0.8.4
